validator_and_token_generator/__init__.py
validator_and_token_generator/validator_and_token_generator.py
validator_and_token_generator-0.1.0.dist-info/LICENSE
validator_and_token_generator-0.1.0.dist-info/METADATA
validator_and_token_generator-0.1.0.dist-info/WHEEL
validator_and_token_generator-0.1.0.dist-info/top_level.txt
validator_and_token_generator-0.1.0.dist-info/RECORD
