Metadata-Version: 2.1
Name: validator-and-token-generator
Version: 0.1.0
Summary: Python package for string validation and alphanumeric token generation
Home-page: https://github.com/SasheO/CS3_Project
Download-URL: https://github.com/SasheO/CS3_Project/0.1.0.tar.gz
Author: SasheO, Xaiver71, emilyyjx
Author-email: mezisashe.ojuba@bison.howard.edu, malcolm.gray@bison.howard.edu, emily.jones@bison.howard.edu
Classifier: Programming Language :: Python :: 3
Classifier: License :: OSI Approved :: MIT License
Classifier: Operating System :: OS Independent
Requires-Python: >=3
License-File: LICENSE
Requires-Dist: secrets
